MANIFEST.in
README.rst
setup.cfg
setup.py
nosedbreport/__init__.py
nosedbreport/base.py
nosedbreport/mysql.py
nosedbreport/plugin.py
nosedbreport/sqlite.py
nosedbreport.egg-info/PKG-INFO
nosedbreport.egg-info/SOURCES.txt
nosedbreport.egg-info/dependency_links.txt
nosedbreport.egg-info/entry_points.txt
nosedbreport.egg-info/top_level.txt