Metadata-Version: 1.0
Name: nosedbreport
Version: 0.2.9
Summary: Nose plugin for recording test results to a database
Home-page: https://nosedbreport.readthedocs.org/en/latest/
Author: Ali-Akber Saifee
Author-email: ali@indydevs.org
License: MIT
Platform: UNKNOWN
